{
  "restaurants": [
    {
      "id": 1,
      "name": "The Biryani House",
      "cuisine": "Indian, Biryani",
      "rating": 4.5,
      "deliveryTime": "30 mins",
      "image": "https://source.unsplash.com/600x400/?biryani",
      "menu": [
        {
          "id": 101,
          "name": "Hyderabadi Chicken Biryani",
          "price": 250,
          "description": "Spicy rice with chicken and authentic Hyderabadi flavor",
          "image": "https://source.unsplash.com/600x400/?chicken-biryani"
        }
      ]
    }
  ]
}
